tests/__init__.py
tests/black_mirror.py
tests/utility_tests.py
tests/test_main/__init__.py
tests/test_main/manage.py
tests/test_main/wikibase_tests.py
tests/test_main/datatypes/__init__.py
tests/test_main/datatypes/models.py
tests/test_main/datatypes/tests.py
tests/test_main/dates/__init__.py
tests/test_main/dates/models.py
tests/test_main/dates/tests.py
tests/test_main/datetimes/__init__.py
tests/test_main/datetimes/models.py
tests/test_main/datetimes/tests.py
tests/test_main/expressions/__init__.py
tests/test_main/expressions/models.py
tests/test_main/expressions/tests.py
tests/test_main/inspectdb/__init__.py
tests/test_main/inspectdb/models.py
tests/test_main/inspectdb/tests.py
tests/test_main/introspection/__init__.py
tests/test_main/introspection/models.py
tests/test_main/introspection/tests.py
tests/test_main/lookup/__init__.py
tests/test_main/lookup/models.py
tests/test_main/lookup/test_timefield.py
tests/test_main/lookup/tests.py
tests/test_main/many_to_one/__init__.py
tests/test_main/many_to_one/models.py
tests/test_main/many_to_one/tests.py
tests/test_main/model_fields/__init__.py
tests/test_main/model_fields/basic_field_tests.py
tests/test_main/model_fields/binary_field_tests.py
tests/test_main/model_fields/boolean_field_tests.py
tests/test_main/model_fields/char_field_tests.py
tests/test_main/model_fields/date_time_field_tests.py
tests/test_main/model_fields/decimal_field_tests.py
tests/test_main/model_fields/duration_field_tests.py
tests/test_main/model_fields/field_flags_tests.py
tests/test_main/model_fields/file_field_tests.py
tests/test_main/model_fields/floatfield_tests.py
tests/test_main/model_fields/foreign_key_tests.py
tests/test_main/model_fields/generic_ip_address_field_tests.py
tests/test_main/model_fields/image_field_tests.py
tests/test_main/model_fields/integer_field_tests.py
tests/test_main/model_fields/many_to_many_field_tests.py
tests/test_main/model_fields/models.py
tests/test_main/model_fields/promises_tests.py
django_wikibase-0.1.1a9.dist-info/LICENSE
django_wikibase-0.1.1a9.dist-info/METADATA
django_wikibase-0.1.1a9.dist-info/WHEEL
django_wikibase-0.1.1a9.dist-info/top_level.txt
django_wikibase-0.1.1a9.dist-info/RECORD
